yaqc/HandshakeRequest.avsc
yaqc/HandshakeResponse.avsc
yaqc/__init__.py
yaqc/__version__.py
yaqc/_avro_numpy.py
yaqc/_client.py
yaqc/_dotdict.py
yaqc/_properties.py
yaqc/_schema.py
yaqc/_socket.py
yaqc-2023.6.0.dist-info/METADATA
yaqc-2023.6.0.dist-info/WHEEL
yaqc-2023.6.0.dist-info/licenses/LICENSE
yaqc-2023.6.0.dist-info/RECORD
